CHANGES
LICENSE
README.txt
bootstrap.py
buildout.cfg
setup.py
iw/__init__.py
iw.subversion.egg-info/PKG-INFO
iw.subversion.egg-info/SOURCES.txt
iw.subversion.egg-info/dependency_links.txt
iw.subversion.egg-info/entry_points.txt
iw.subversion.egg-info/namespace_packages.txt
iw.subversion.egg-info/not-zip-safe
iw.subversion.egg-info/requires.txt
iw.subversion.egg-info/top_level.txt
iw/subversion/README.txt
iw/subversion/__init__.py
iw/subversion/svn_check_source.py
iw/subversion/docs/README.txt
iw/subversion/doctests/README.txt
iw/subversion/tests/__init__.py
iw/subversion/tests/rotten.py
iw/subversion/tests/test_subversiondocs.py
iw/subversion/tests/test_subversiondocstrings.py
iw/subversion/tests/test_svn_check_source.py
