Metadata-Version: 1.0
Name: iw.subversion
Version: 0.1.0
Summary: Contains hooks and utilities for Subversion
Home-page: https://ingeniweb.svn.sourceforge.net/svnroot/ingeniweb/iw.subversion
Author: Ingeniweb
Author-email: support@ingeniweb.com
License: GPL
Keywords: subversion commit hook
Platform: UNKNOWN
Classifier: Programming Language :: Python
Classifier: Topic :: Software Development :: Libraries :: Python Modules
